examples/device/__main__.py
examples/device/image.py
examples/helloworld/__init__.py
examples/helloworld/__main__.py
examples/helloworld/session.py
examples/telemetry_demo/__init__.py
examples/telemetry_demo/__main__.py
examples/telemetry_demo/service.py
oaas_sdk2_py/__init__.py
oaas_sdk2_py/config.py
oaas_sdk2_py/engine.py
oaas_sdk2_py/handler.py
oaas_sdk2_py/mock.py
oaas_sdk2_py/model.py
oaas_sdk2_py/obj.py
oaas_sdk2_py/repo.py
oaas_sdk2_py/rpc_futures.py
oaas_sdk2_py/session.py
oaas_sdk2_py/telemetry.py
oaas_sdk2_py/simplified/__init__.py
oaas_sdk2_py/simplified/accessors.py
oaas_sdk2_py/simplified/config.py
oaas_sdk2_py/simplified/decorators.py
oaas_sdk2_py/simplified/errors.py
oaas_sdk2_py/simplified/objects.py
oaas_sdk2_py/simplified/performance.py
oaas_sdk2_py/simplified/references.py
oaas_sdk2_py/simplified/serialization.py
oaas_sdk2_py/simplified/service.py
oaas_sdk2_py/simplified/session_manager.py
oaas_sdk2_py/simplified/state_descriptor.py
oprc-py/oprc_py/__init__.py
oprc-py/oprc_py/oprc_py.pyi
oprc-py/oprc_py/py.typed
oprc-py/tests/test.py
tests/__init__.py
tests/conftest.py
tests/sample_cls.py
tests/integration/test_rpc_system.py
tests/integration/test_session_management.py
tests/integration/test_session_transitive_calls.py
tests/integration/test_simplified_compatibility.py
tests/server/test_serve.py
tests/server/test_server_agent_management.py
tests/shared/helpers.py
tests/shared/services.py
tests/unit/test_accessors.py
tests/unit/test_comprehensive_foundation.py
tests/unit/test_constructor_and_setter_proxy.py
tests/unit/test_dict_functions.py
tests/unit/test_enhanced_decorators.py
tests/unit/test_enhanced_serialization.py
tests/unit/test_event.py
tests/unit/test_mock.py
tests/unit/test_parameter_types.py
tests/unit/test_primitive_types.py
tests/unit/test_references.py
tests/unit/test_sync_accessors.py
oaas_sdk2_py-0.3.6.dist-info/METADATA
oaas_sdk2_py-0.3.6.dist-info/WHEEL
oaas_sdk2_py-0.3.6.dist-info/top_level.txt
oaas_sdk2_py-0.3.6.dist-info/RECORD
