Metadata-Version: 2.4
Name: oaas-sdk2-py
Version: 0.3.6
Requires-Python: >=3.11
Requires-Dist: uvloop>=0.21.0; sys_platform != "win32"
Requires-Dist: winloop>=0.1.8; sys_platform == "win32"
Requires-Dist: pydantic>=2.11.6
Requires-Dist: pydantic-settings>=2.10.1
Requires-Dist: pyyaml>=6.0.2
Requires-Dist: tsidpy>=1.1.5
Requires-Dist: oprc-py>=0.3.3
